chromedriver_autoinstaller_max/__init__.py
chromedriver_autoinstaller_max/utils.py
chromedriver_autoinstaller_max-1.0.6.dist-info/LICENSE
chromedriver_autoinstaller_max-1.0.6.dist-info/METADATA
chromedriver_autoinstaller_max-1.0.6.dist-info/WHEEL
chromedriver_autoinstaller_max-1.0.6.dist-info/entry_points.txt
chromedriver_autoinstaller_max-1.0.6.dist-info/top_level.txt
chromedriver_autoinstaller_max-1.0.6.dist-info/RECORD
